CHANGELOG
LICENSE
MANIFEST.in
README.txt
TODO
requirements.txt
setup.cfg
setup.py
WebHelpers.egg-info/PKG-INFO
WebHelpers.egg-info/SOURCES.txt
WebHelpers.egg-info/dependency_links.txt
WebHelpers.egg-info/entry_points.txt
WebHelpers.egg-info/not-zip-safe
WebHelpers.egg-info/top_level.txt
docs/Makefile
docs/changelog.rst
docs/conf.py
docs/contents.rst
docs/development.rst
docs/third_party.rst
docs/todo.rst
docs/whats_new.rst
docs/_static/default.css
docs/_static/webhelpers-logo.png
docs/_templates/index.html
docs/_templates/indexsidebar.html
docs/_templates/layout.html
docs/modules/constants.rst
docs/modules/containers.rst
docs/modules/date.rst
docs/modules/feedgenerator.rst
docs/modules/markdown.rst
docs/modules/media.rst
docs/modules/mimehelper.rst
docs/modules/misc.rst
docs/modules/number.rst
docs/modules/paginate.rst
docs/modules/text.rst
docs/modules/textile.rst
docs/modules/util.rst
docs/modules/html/__init__.rst
docs/modules/html/builder.rst
docs/modules/html/converters.rst
docs/modules/html/grid.rst
docs/modules/html/tags.rst
docs/modules/html/tools.rst
docs/modules/pylonslib/__init__.rst
docs/modules/pylonslib/flash.rst
docs/modules/pylonslib/grid.rst
docs/modules/pylonslib/minify.rst
docs/modules/pylonslib/secure_form.rst
tests/test_containers.py
tests/test_converters.py
tests/test_date.py
tests/test_escapes.py
tests/test_feedgenerator.py
tests/test_html.py
tests/test_mimetypes.py
tests/test_misc.py
tests/test_modeltags.py
tests/test_number.py
tests/test_paginate.py
tests/test_pylonslib_flash.py
tests/test_tags.py
tests/test_text.py
tests/test_tools.py
tests/util.py
unfinished/README
unfinished/baseN.py
unfinished/containers.py
unfinished/disabled_test_pylonslib_minify.py
unfinished/document.py
unfinished/logging_optparse.py
unfinished/multimedia.py
unfinished/number_to_human_size.py
unfinished/opener.py
unfinished/sanitize_filename.py
webhelpers/__init__.py
webhelpers/constants.py
webhelpers/containers.py
webhelpers/date.py
webhelpers/feedgenerator.py
webhelpers/markdown.py
webhelpers/media.py
webhelpers/mimehelper.py
webhelpers/misc.py
webhelpers/number.py
webhelpers/paginate.py
webhelpers/text.py
webhelpers/textile.py
webhelpers/util.py
