Metadata-Version: 1.0
Name: WebHelpers
Version: 1.1
Summary: Web Helpers
Home-page: http://webhelpers.groovie.org/
Author: Mike Orr, Ben Bangert, Phil Jenvey
Author-email: sluggoster@gmail.com, ben@groovie.org, pjenvey@groovie.org
License: UNKNOWN
Platform: UNKNOWN
Classifier: Development Status :: 4 - Beta
Classifier: Intended Audience :: Developers
Classifier: License :: OSI Approved :: BSD License
Classifier: Programming Language :: Python
Classifier: Topic :: Internet :: WWW/HTTP :: Dynamic Content
Classifier: Topic :: Software Development :: Libraries :: Python Modules
